PyWebFramework-1.1.data/data/pyWebFramework/dll/CertUtility.dll
PyWebFramework-1.1.data/data/pyWebFramework/dll/ErrorCode.dll
PyWebFramework-1.1.data/data/pyWebFramework/dll/HttpCommon.dll
PyWebFramework-1.1.data/data/pyWebFramework/dll/HttpNet.dll
PyWebFramework-1.1.data/data/pyWebFramework/dll/IeWebFramework.pyd
PyWebFramework-1.1.data/data/pyWebFramework/dll/LogExt.dll
PyWebFramework-1.1.data/data/pyWebFramework/dll/WebBrowser.dll
PyWebFramework-1.1.data/data/pyWebFramework/dll/YzmOCR.dll
PyWebFramework-1.1.data/data/pyWebFramework/dll/YzmOCR.pyd
PyWebFramework-1.1.data/data/pyWebFramework/dll/ajaxhook.min.js
PyWebFramework-1.1.data/data/pyWebFramework/dll/boost_python37-vc141-mt-gd-x32-1_70.dll
PyWebFramework-1.1.data/data/pyWebFramework/dll/jquery.min.js
PyWebFramework-1.1.data/data/pyWebFramework/dll/jsoncpp.dll
PyWebFramework-1.1.data/data/pyWebFramework/dll/libcrypto-1_1.dll
PyWebFramework-1.1.data/data/pyWebFramework/dll/msvcp140d.dll
PyWebFramework-1.1.data/data/pyWebFramework/dll/pswem2.dll
PyWebFramework-1.1.data/data/pyWebFramework/dll/ucrtbased.dll
PyWebFramework-1.1.data/data/pyWebFramework/dll/vcruntime140d.dll
pyWebFramework/__init__.py
pyWebFramework/loader.py
pyWebFramework/core/__init__.py
pyWebFramework/core/error.py
pyWebFramework/core/exception.py
pyWebFramework/core/module.py
pyWebFramework/core/page.py
pyWebFramework/core/settings.py
pyWebFramework/core/task.py
pyWebFramework/dll/__init__.py
pyWebFramework/tax_init/PageTaxInitFormBase.py
pyWebFramework/tax_init/Swinit.py
pyWebFramework/tax_init/TaskTaxInitBase.py
pyWebFramework/tax_init/__init__.py
PyWebFramework-1.1.dist-info/METADATA
PyWebFramework-1.1.dist-info/WHEEL
PyWebFramework-1.1.dist-info/top_level.txt
PyWebFramework-1.1.dist-info/RECORD
