Metadata-Version: 2.1
Name: PyWebFramework
Version: 1.1
Summary: Web Framework
Home-page: UNKNOWN
Author: peng
Author-email: UNKNOWN
License: UNKNOWN
Platform: UNKNOWN
